{
  "$schema": "https://ui.shadcn.com/schema/registry-item.json",
  "name": "ContextMenuGroups",
  "dependencies": [],
  "files": [
    {
      "path": "registry/base/examples/ContextMenuGroups.res",
      "content": "@react.component\nlet make = () =>\n  <ContextMenu>\n    <ContextMenu.Trigger\n      className=\"flex aspect-video w-full max-w-xs items-center justify-center rounded-xl border border-dashed text-sm\"\n    >\n      <span className=\"hidden pointer-fine:inline-block\"> {\"Right click here\"->React.string} </span>\n      <span className=\"hidden pointer-coarse:inline-block\">\n        {\"Long press here\"->React.string}\n      </span>\n    </ContextMenu.Trigger>\n    <ContextMenu.Content>\n      <ContextMenu.Group>\n        <ContextMenu.Label> {\"File\"->React.string} </ContextMenu.Label>\n        <ContextMenu.Item>\n          {\"New File\"->React.string}\n          <ContextMenu.Shortcut> {\"\\u2318N\"->React.string} </ContextMenu.Shortcut>\n        </ContextMenu.Item>\n        <ContextMenu.Item>\n          {\"Open File\"->React.string}\n          <ContextMenu.Shortcut> {\"\\u2318O\"->React.string} </ContextMenu.Shortcut>\n        </ContextMenu.Item>\n        <ContextMenu.Item>\n          {\"Save\"->React.string}\n          <ContextMenu.Shortcut> {\"\\u2318S\"->React.string} </ContextMenu.Shortcut>\n        </ContextMenu.Item>\n      </ContextMenu.Group>\n      <ContextMenu.Separator />\n      <ContextMenu.Group>\n        <ContextMenu.Label> {\"Edit\"->React.string} </ContextMenu.Label>\n        <ContextMenu.Item>\n          {\"Undo\"->React.string}\n          <ContextMenu.Shortcut> {\"\\u2318Z\"->React.string} </ContextMenu.Shortcut>\n        </ContextMenu.Item>\n        <ContextMenu.Item>\n          {\"Redo\"->React.string}\n          <ContextMenu.Shortcut> {\"\\u21e7\\u2318Z\"->React.string} </ContextMenu.Shortcut>\n        </ContextMenu.Item>\n      </ContextMenu.Group>\n      <ContextMenu.Separator />\n      <ContextMenu.Group>\n        <ContextMenu.Item>\n          {\"Cut\"->React.string}\n          <ContextMenu.Shortcut> {\"\\u2318X\"->React.string} </ContextMenu.Shortcut>\n        </ContextMenu.Item>\n        <ContextMenu.Item>\n          {\"Copy\"->React.string}\n          <ContextMenu.Shortcut> {\"\\u2318C\"->React.string} </ContextMenu.Shortcut>\n        </ContextMenu.Item>\n        <ContextMenu.Item>\n          {\"Paste\"->React.string}\n          <ContextMenu.Shortcut> {\"\\u2318V\"->React.string} </ContextMenu.Shortcut>\n        </ContextMenu.Item>\n      </ContextMenu.Group>\n      <ContextMenu.Separator />\n      <ContextMenu.Group>\n        <ContextMenu.Item variant=ContextMenu.Variant.Destructive>\n          {\"Delete\"->React.string}\n          <ContextMenu.Shortcut> {\"\\u232b\"->React.string} </ContextMenu.Shortcut>\n        </ContextMenu.Item>\n      </ContextMenu.Group>\n    </ContextMenu.Content>\n  </ContextMenu>\n",
      "type": "registry:example"
    }
  ],
  "type": "registry:example"
}