{
  "$schema": "https://ui.shadcn.com/schema/registry-item.json",
  "name": "DatePickerRtl",
  "dependencies": [],
  "files": [
    {
      "path": "registry/base/examples/DatePickerRtl.res",
      "content": "@@directive(\"'use client'\")\n\ntype dateFnsLocale\n@module(\"date-fns/locale\") external arSA: dateFnsLocale = \"arSA\"\ntype dateFnsFormatOpts = {locale: dateFnsLocale}\n@module(\"date-fns\") external format: (Date.t, string) => string = \"format\"\n@module(\"date-fns\")\nexternal formatWithLocale: (Date.t, string, dateFnsFormatOpts) => string = \"format\"\n\n@module(\"react-day-picker/locale\") external arSADayPicker: Calendar.Locale.t = \"arSA\"\n\n@react.component\nlet make = () => {\n  let (date, setDate) = React.useState(() => None)\n\n  <Popover>\n    <Popover.Trigger\n      render={<Button\n        variant=Button.Variant.Outline\n        dataEmpty=?{date->Option.isNone ? Some(true) : None}\n        className=\"data-[empty=true]:text-muted-foreground w-[212px] justify-between text-left font-normal\"\n        dir=\"rtl\"\n      />}\n    >\n      {switch date {\n      | Some(d) => d->formatWithLocale(\"PPP\", {locale: arSA})->React.string\n      | None => <span> {\"اختر تاريخًا\"->React.string} </span>\n      }}\n      <Icons.ChevronDown dataIcon=\"inline-end\" />\n    </Popover.Trigger>\n    <Popover.Content className=\"w-auto p-0\" align=BaseUi.Types.Align.Start dir=\"rtl\">\n      <Calendar\n        mode=\"single\"\n        selected={date}\n        onSelect={(value: option<Date.t>) => setDate(_ => value)}\n        defaultMonth=?{date}\n        dir=\"rtl\"\n        locale={arSADayPicker}\n      />\n    </Popover.Content>\n  </Popover>\n}\n",
      "type": "registry:example"
    }
  ],
  "type": "registry:example"
}